{
  "source_file": "013_seycoffee.com_collections_archived-coffees_products_2025-kayu-aa-separation-kenya.html",
  "processed_at": "2025-06-19T15:38:45.986772",
  "coffee_beans": [
    {
      "name": "Kayu AA SEPARATION FIELD BLEND - WASHED Kenya",
      "producer": "Kayu Coffee Factory",
      "region": "Murang'a County, Kenya",
      "roast_level": "MEDIUM",
      "flavor_notes": [
        "blackcurrant",
        "hibiscus",
        "Key lime"
      ],
      "grind_type": "WHOLE_BEAN"
    }
  ],
  "beans_found": 1
}